{
  "id": "hoiquan",
  "url": "https://sv2.hoiquan3.live",
  "name": "HoiQuanTV",
  "color": "#1cb57a",
  "updated_at": "21:30 25/05/2026",
  "grid_number": 3,
  "image": {
    "type": "cover",
    "url": "https://sv2.hoiquan3.live/logo.png"
  },
  "groups": [
    {
      "id": "sport_bong-da",
      "name": "⚽ Bóng Đá",
      "display": "vertical",
      "grid_number": 2,
      "enable_detail": false,
      "channels": [
        {
          "id": "hqlive-47c804b7d3",
          "name": "Sarpsborg 08 FF vs Molde | 22:00 25/05",
          "type": "single",
          "display": "thumbnail-only",
          "enable_detail": false,
          "labels": [
            {
              "text": "🕐 Sắp",
              "position": "top-left",
              "color": "#00000080",
              "text_color": "#aaaaaa"
            }
          ],
          "sources": [
            {
              "id": "src-47c804b7d3",
              "name": "HoiQuanTV",
              "contents": [
                {
                  "id": "ct-47c804b7d3",
                  "name": "Sarpsborg 08 FF vs Molde",
                  "streams": [
                    {
                      "id": "st-47c804b7d3",
                      "name": "HQ",
                      "stream_links": []
                    }
                  ]
                }
              ]
            }
          ],
          "org_metadata": {
            "league": "Eliteserien",
            "team_a": "Sarpsborg 08 FF",
            "team_b": "Molde",
            "logo_a": "https://media.api-sports.io/football/teams/333.png",
            "logo_b": "https://media.api-sports.io/football/teams/329.png",
            "time": "22:00 25/05",
            "blv": "BLV PHAN CA",
            "is_live": false,
            "sport_slug": "bong-da"
          },
          "image": {
            "padding": 1,
            "background_color": "#ffffff",
            "display": "contain",
            "url": "https://raw.githubusercontent.com/jasminliu98/hoiquan-stream/refs/heads/main/thumbs/Sarpsborg 08 FF_Molde_22-00 25-05_6c396c56_20260525.png?v=6c396c56",
            "width": 1600,
            "height": 1200
          }
        },
        {
          "id": "hqlive-699c65b1f9",
          "name": "SC Paderborn 07 vs VfL Wolfsburg | 01:30 26/05",
          "type": "single",
          "display": "thumbnail-only",
          "enable_detail": false,
          "labels": [
            {
              "text": "🕐 Sắp",
              "position": "top-left",
              "color": "#00000080",
              "text_color": "#aaaaaa"
            }
          ],
          "sources": [
            {
              "id": "src-699c65b1f9",
              "name": "HoiQuanTV",
              "contents": [
                {
                  "id": "ct-699c65b1f9",
                  "name": "SC Paderborn 07 vs VfL Wolfsburg",
                  "streams": [
                    {
                      "id": "st-699c65b1f9",
                      "name": "HQ",
                      "stream_links": []
                    }
                  ]
                }
              ]
            }
          ],
          "org_metadata": {
            "league": "Bundesliga",
            "team_a": "SC Paderborn 07",
            "team_b": "VfL Wolfsburg",
            "logo_a": "https://dothethao.net.vn/wp-content/uploads/2020/06/sc-paderborn-logo-900px.png",
            "logo_b": "https://upload.wikimedia.org/wikipedia/commons/thumb/c/ce/VfL_Wolfsburg_Logo.svg/1280px-VfL_Wolfsburg_Logo.svg.png",
            "time": "01:30 26/05",
            "blv": "BLV PHAN CA",
            "is_live": false,
            "sport_slug": "bong-da"
          },
          "image": {
            "padding": 1,
            "background_color": "#ffffff",
            "display": "contain",
            "url": "https://raw.githubusercontent.com/jasminliu98/hoiquan-stream/refs/heads/main/thumbs/SC Paderborn 07_VfL Wolfsburg_01-30 26-05_e735ca5d_20260525.png?v=e735ca5d",
            "width": 1600,
            "height": 1200
          }
        },
        {
          "id": "hqlive-4334889231",
          "name": "Coritiba vs Bahia | 06:00 26/05",
          "type": "single",
          "display": "thumbnail-only",
          "enable_detail": false,
          "labels": [
            {
              "text": "🕐 Sắp",
              "position": "top-left",
              "color": "#00000080",
              "text_color": "#aaaaaa"
            }
          ],
          "sources": [
            {
              "id": "src-4334889231",
              "name": "HoiQuanTV",
              "contents": [
                {
                  "id": "ct-4334889231",
                  "name": "Coritiba vs Bahia",
                  "streams": [
                    {
                      "id": "st-4334889231",
                      "name": "HQ",
                      "stream_links": []
                    }
                  ]
                }
              ]
            }
          ],
          "org_metadata": {
            "league": "VĐQG Brazil ",
            "team_a": "Coritiba",
            "team_b": "Bahia",
            "logo_a": "https://upload.wikimedia.org/wikipedia/commons/thumb/b/bd/Coritiba_Foot_Ball_Club_logo.svg/500px-Coritiba_Foot_Ball_Club_logo.svg.png",
            "logo_b": "https://upload.wikimedia.org/wikipedia/commons/thumb/1/1e/Logo_of_Esporte_Clube_Bahia_%282004%29.svg/250px-Logo_of_Esporte_Clube_Bahia_%282004%29.svg.png",
            "time": "06:00 26/05",
            "blv": "BLV PHAN ANH",
            "is_live": false,
            "sport_slug": "bong-da"
          },
          "image": {
            "padding": 1,
            "background_color": "#ffffff",
            "display": "contain",
            "url": "https://raw.githubusercontent.com/jasminliu98/hoiquan-stream/refs/heads/main/thumbs/Coritiba_Bahia_06-00 26-05_8cd37d33_20260525.png?v=8cd37d33",
            "width": 1600,
            "height": 1200
          }
        }
      ]
    },
    {
      "id": "sport_billiards",
      "name": "🎱 Billiards",
      "display": "vertical",
      "grid_number": 2,
      "enable_detail": false,
      "channels": [
        {
          "id": "hqlive-8f168a9e76",
          "name": "Tay cơ 1 vs Tay cơ 2 | 18:00 26/05",
          "type": "single",
          "display": "thumbnail-only",
          "enable_detail": false,
          "labels": [
            {
              "text": "🕐 Sắp",
              "position": "top-left",
              "color": "#00000080",
              "text_color": "#aaaaaa"
            }
          ],
          "sources": [
            {
              "id": "src-8f168a9e76",
              "name": "HoiQuanTV",
              "contents": [
                {
                  "id": "ct-8f168a9e76",
                  "name": "Tay cơ 1 vs Tay cơ 2",
                  "streams": [
                    {
                      "id": "st-8f168a9e76",
                      "name": "HQ",
                      "stream_links": []
                    }
                  ]
                }
              ]
            }
          ],
          "org_metadata": {
            "league": "UK OPEN",
            "team_a": "Tay cơ 1",
            "team_b": "Tay cơ 2",
            "logo_a": "https://img.freepik.com/vector-mien-phi/mau-thiet-ke-logo-billiard_23-2150883890.jpg",
            "logo_b": "https://img.freepik.com/vector-mien-phi/mau-thiet-ke-logo-billiard_23-2150883890.jpg",
            "time": "18:00 26/05",
            "blv": "BLV PHAN ANH",
            "is_live": false,
            "sport_slug": "billiards"
          },
          "image": {
            "padding": 1,
            "background_color": "#ffffff",
            "display": "contain",
            "url": "https://raw.githubusercontent.com/jasminliu98/hoiquan-stream/refs/heads/main/thumbs/Tay cơ 1_Tay cơ 2_18-00 26-05_97f1b445_20260525.png?v=97f1b445",
            "width": 1600,
            "height": 1200
          }
        },
        {
          "id": "hqlive-285e0bcb59",
          "name": "Tay cơ 1 vs Tay cơ 2 | 21:00 26/05",
          "type": "single",
          "display": "thumbnail-only",
          "enable_detail": false,
          "labels": [
            {
              "text": "🕐 Sắp",
              "position": "top-left",
              "color": "#00000080",
              "text_color": "#aaaaaa"
            }
          ],
          "sources": [
            {
              "id": "src-285e0bcb59",
              "name": "HoiQuanTV",
              "contents": [
                {
                  "id": "ct-285e0bcb59",
                  "name": "Tay cơ 1 vs Tay cơ 2",
                  "streams": [
                    {
                      "id": "st-285e0bcb59",
                      "name": "HQ",
                      "stream_links": []
                    }
                  ]
                }
              ]
            }
          ],
          "org_metadata": {
            "league": "UK OPEN",
            "team_a": "Tay cơ 1",
            "team_b": "Tay cơ 2",
            "logo_a": "https://img.freepik.com/vector-mien-phi/mau-thiet-ke-logo-billiard_23-2150883890.jpg",
            "logo_b": "https://img.freepik.com/vector-mien-phi/mau-thiet-ke-logo-billiard_23-2150883890.jpg",
            "time": "21:00 26/05",
            "blv": "BLV LƯƠNG BỔNG",
            "is_live": false,
            "sport_slug": "billiards"
          },
          "image": {
            "padding": 1,
            "background_color": "#ffffff",
            "display": "contain",
            "url": "https://raw.githubusercontent.com/jasminliu98/hoiquan-stream/refs/heads/main/thumbs/Tay cơ 1_Tay cơ 2_21-00 26-05_97f1b445_20260525.png?v=97f1b445",
            "width": 1600,
            "height": 1200
          }
        }
      ]
    },
    {
      "id": "sport_bong-ro",
      "name": "🏀 Bóng Rổ",
      "display": "vertical",
      "grid_number": 2,
      "enable_detail": false,
      "channels": [
        {
          "id": "hqlive-c4097c015c",
          "name": "Cleveland Cavaliers vs New York Knicks | 07:00 26/05",
          "type": "single",
          "display": "thumbnail-only",
          "enable_detail": false,
          "labels": [
            {
              "text": "🕐 Sắp",
              "position": "top-left",
              "color": "#00000080",
              "text_color": "#aaaaaa"
            }
          ],
          "sources": [
            {
              "id": "src-c4097c015c",
              "name": "HoiQuanTV",
              "contents": [
                {
                  "id": "ct-c4097c015c",
                  "name": "Cleveland Cavaliers vs New York Knicks",
                  "streams": [
                    {
                      "id": "st-c4097c015c",
                      "name": "HQ",
                      "stream_links": []
                    }
                  ]
                }
              ]
            }
          ],
          "org_metadata": {
            "league": "NBA",
            "team_a": "Cleveland Cavaliers",
            "team_b": "New York Knicks",
            "logo_a": "https://encrypted-tbn0.gstatic.com/images?q=tbn:ANd9GcSON_xAXqlmVA6CaABNgxtXMaVaFZIg65IPrg&s",
            "logo_b": "https://upload.wikimedia.org/wikipedia/en/2/25/New_York_Knicks_logo.svg",
            "time": "07:00 26/05",
            "blv": "BLV PHAN TỪ",
            "is_live": false,
            "sport_slug": "bong-ro"
          },
          "image": {
            "padding": 1,
            "background_color": "#ffffff",
            "display": "contain",
            "url": "https://raw.githubusercontent.com/jasminliu98/hoiquan-stream/refs/heads/main/thumbs/Cleveland Cavaliers_New York Knicks_07-00 26-05_0d71be6e_20260525.png?v=0d71be6e",
            "width": 1600,
            "height": 1200
          }
        },
        {
          "id": "hqlive-0af4fba76b",
          "name": "Oklahoma City Thunder vs San Antonio Spurs | 07:30 27/05",
          "type": "single",
          "display": "thumbnail-only",
          "enable_detail": false,
          "labels": [
            {
              "text": "🕐 Sắp",
              "position": "top-left",
              "color": "#00000080",
              "text_color": "#aaaaaa"
            }
          ],
          "sources": [
            {
              "id": "src-0af4fba76b",
              "name": "HoiQuanTV",
              "contents": [
                {
                  "id": "ct-0af4fba76b",
                  "name": "Oklahoma City Thunder vs San Antonio Spurs",
                  "streams": [
                    {
                      "id": "st-0af4fba76b",
                      "name": "HQ",
                      "stream_links": []
                    }
                  ]
                }
              ]
            }
          ],
          "org_metadata": {
            "league": "NBA",
            "team_a": "Oklahoma City Thunder",
            "team_b": "San Antonio Spurs",
            "logo_a": "https://encrypted-tbn0.gstatic.com/images?q=tbn:ANd9GcS0x_r4HXgpRt8N2PALEejkBLGLqf4VYCZmhg&s",
            "logo_b": "https://upload.wikimedia.org/wikipedia/vi/e/ec/San_Antonio_Spurs_logo.png",
            "time": "07:30 27/05",
            "blv": "BLV PHAN TỪ",
            "is_live": false,
            "sport_slug": "bong-ro"
          },
          "image": {
            "padding": 1,
            "background_color": "#ffffff",
            "display": "contain",
            "url": "https://raw.githubusercontent.com/jasminliu98/hoiquan-stream/refs/heads/main/thumbs/Oklahoma City Thunder_San Antonio Spurs_07-30 27-05_280346f3_20260525.png?v=280346f3",
            "width": 1600,
            "height": 1200
          }
        }
      ]
    },
    {
      "id": "sport_tennis",
      "name": "🎾 Tennis (1 LIVE)",
      "display": "vertical",
      "grid_number": 2,
      "enable_detail": false,
      "channels": [
        {
          "id": "hqlive-0a2ca849d5",
          "name": "Stan Wawrinka vs Jesper De Jong | 18:00 25/05",
          "type": "single",
          "display": "thumbnail-only",
          "enable_detail": false,
          "labels": [
            {
              "text": "● LIVE",
              "position": "top-left",
              "color": "#00000080",
              "text_color": "#ff4444"
            }
          ],
          "sources": [
            {
              "id": "src-0a2ca849d5",
              "name": "HoiQuanTV",
              "contents": [
                {
                  "id": "ct-0a2ca849d5",
                  "name": "Stan Wawrinka vs Jesper De Jong",
                  "streams": [
                    {
                      "id": "st-0a2ca849d5",
                      "name": "HQ",
                      "stream_links": [
                        {
                          "id": "lnk-f6231c6549",
                          "name": "BLV PHAN CA",
                          "type": "hls",
                          "default": true,
                          "url": "https://hqlive.yarncdn.live/live/hqtv_blv_phanca/playlist.m3u8",
                          "request_headers": [
                            {
                              "key": "Referer",
                              "value": "https://sv2.hoiquan3.live/"
                            },
                            {
                              "key": "User-Agent",
                              "value": "Mozilla/5.0"
                            }
                          ]
                        }
                      ]
                    }
                  ]
                }
              ]
            }
          ],
          "org_metadata": {
            "league": "Roland Garros",
            "team_a": "Stan Wawrinka",
            "team_b": "Jesper De Jong",
            "logo_a": "https://upload.wikimedia.org/wikipedia/commons/thumb/d/d9/Wawrinka_RG19_%2816%29_%2848199015787%29.jpg/960px-Wawrinka_RG19_%2816%29_%2848199015787%29.jpg",
            "logo_b": "https://encrypted-tbn0.gstatic.com/images?q=tbn:ANd9GcTJcxagp0vS3vukoZ6vA2xY3KVhGTKDKtIP7w&s",
            "time": "18:00 25/05",
            "blv": "BLV PHAN CA",
            "is_live": true,
            "sport_slug": "tennis"
          },
          "image": {
            "padding": 1,
            "background_color": "#ffffff",
            "display": "contain",
            "url": "https://raw.githubusercontent.com/jasminliu98/hoiquan-stream/refs/heads/main/thumbs/Stan Wawrinka_Jesper De Jong_18-00 25-05_f229e713_20260525.png?v=f229e713",
            "width": 1600,
            "height": 1200
          }
        },
        {
          "id": "hqlive-f32e040195",
          "name": "Daniel Merida vs Ben Shelton | 22:00 25/05",
          "type": "single",
          "display": "thumbnail-only",
          "enable_detail": false,
          "labels": [
            {
              "text": "🕐 Sắp",
              "position": "top-left",
              "color": "#00000080",
              "text_color": "#aaaaaa"
            }
          ],
          "sources": [
            {
              "id": "src-f32e040195",
              "name": "HoiQuanTV",
              "contents": [
                {
                  "id": "ct-f32e040195",
                  "name": "Daniel Merida vs Ben Shelton",
                  "streams": [
                    {
                      "id": "st-f32e040195",
                      "name": "HQ",
                      "stream_links": []
                    }
                  ]
                }
              ]
            }
          ],
          "org_metadata": {
            "league": "Roland Garros",
            "team_a": "Daniel Merida",
            "team_b": "Ben Shelton",
            "logo_a": "https://cdn.prod.website-files.com/643e87bf05428401f6b2c705/6638b0089c2b8dc14e652d4f_IMG_BIO_Darina_Webflow.png",
            "logo_b": "https://www.thesecondserve.com/wp-content/uploads/2025/08/ben-shelton-toronto-cincinnati-open2-1.jpg",
            "time": "22:00 25/05",
            "blv": "BLV PHAN TỪ",
            "is_live": false,
            "sport_slug": "tennis"
          },
          "image": {
            "padding": 1,
            "background_color": "#ffffff",
            "display": "contain",
            "url": "https://raw.githubusercontent.com/jasminliu98/hoiquan-stream/refs/heads/main/thumbs/Daniel Merida_Ben Shelton_22-00 25-05_48333568_20260525.png?v=48333568",
            "width": 1600,
            "height": 1200
          }
        },
        {
          "id": "hqlive-c6c87c040b",
          "name": "Aryna Sabalenka vs Jessica Bouzas Maneiro | 17:00 26/05",
          "type": "single",
          "display": "thumbnail-only",
          "enable_detail": false,
          "labels": [
            {
              "text": "🕐 Sắp",
              "position": "top-left",
              "color": "#00000080",
              "text_color": "#aaaaaa"
            }
          ],
          "sources": [
            {
              "id": "src-c6c87c040b",
              "name": "HoiQuanTV",
              "contents": [
                {
                  "id": "ct-c6c87c040b",
                  "name": "Aryna Sabalenka vs Jessica Bouzas Maneiro",
                  "streams": [
                    {
                      "id": "st-c6c87c040b",
                      "name": "HQ",
                      "stream_links": []
                    }
                  ]
                }
              ]
            }
          ],
          "org_metadata": {
            "league": "Roland Garros",
            "team_a": "Aryna Sabalenka",
            "team_b": "Jessica Bouzas Maneiro",
            "logo_a": "https://upload.wikimedia.org/wikipedia/commons/b/b8/Sabalenka_WM18_%283%29_%2830063199288%29.jpg",
            "logo_b": "https://encrypted-tbn0.gstatic.com/images?q=tbn:ANd9GcRABku-HEyppakDXMdArYXrPo8MNNgPAohcIA&s",
            "time": "17:00 26/05",
            "blv": "BLV PHAN TỪ",
            "is_live": false,
            "sport_slug": "tennis"
          },
          "image": {
            "padding": 1,
            "background_color": "#ffffff",
            "display": "contain",
            "url": "https://raw.githubusercontent.com/jasminliu98/hoiquan-stream/refs/heads/main/thumbs/Aryna Sabalenka_Jessica Bouzas Maneiro_17-00 26-05_fa3f4334_20260525.png?v=fa3f4334",
            "width": 1600,
            "height": 1200
          }
        },
        {
          "id": "hqlive-4fbee22eb5",
          "name": "Coco Gauff vs Taylor Townsend | 21:00 26/05",
          "type": "single",
          "display": "thumbnail-only",
          "enable_detail": false,
          "labels": [
            {
              "text": "🕐 Sắp",
              "position": "top-left",
              "color": "#00000080",
              "text_color": "#aaaaaa"
            }
          ],
          "sources": [
            {
              "id": "src-4fbee22eb5",
              "name": "HoiQuanTV",
              "contents": [
                {
                  "id": "ct-4fbee22eb5",
                  "name": "Coco Gauff vs Taylor Townsend",
                  "streams": [
                    {
                      "id": "st-4fbee22eb5",
                      "name": "HQ",
                      "stream_links": []
                    }
                  ]
                }
              ]
            }
          ],
          "org_metadata": {
            "league": "Roland Garros",
            "team_a": "Coco Gauff",
            "team_b": "Taylor Townsend",
            "logo_a": "https://encrypted-tbn0.gstatic.com/images?q=tbn:ANd9GcTlSUpEF6Cuye3u7pi15d4mYx1hORj319ljAw&s",
            "logo_b": "https://encrypted-tbn0.gstatic.com/images?q=tbn:ANd9GcQB-D1f3Zw-_uFrFnI0TsxizeP86DrsSCNwlg&s",
            "time": "21:00 26/05",
            "blv": "BLV PHAN TỪ",
            "is_live": false,
            "sport_slug": "tennis"
          },
          "image": {
            "padding": 1,
            "background_color": "#ffffff",
            "display": "contain",
            "url": "https://raw.githubusercontent.com/jasminliu98/hoiquan-stream/refs/heads/main/thumbs/Coco Gauff_Taylor Townsend_21-00 26-05_da1ad6cb_20260525.png?v=da1ad6cb",
            "width": 1600,
            "height": 1200
          }
        }
      ]
    }
  ]
}