{
  "id": "hoiquan",
  "url": "https://sv2.hoiquan3.live",
  "name": "HoiQuanTV",
  "color": "#1cb57a",
  "updated_at": "00:01 18/06/2026",
  "grid_number": 3,
  "image": {
    "type": "cover",
    "url": "https://sv2.hoiquan3.live/logo.png"
  },
  "groups": [
    {
      "id": "sport_bong-da",
      "name": "⚽ Bóng Đá (2 LIVE)",
      "display": "vertical",
      "grid_number": 2,
      "enable_detail": false,
      "channels": [
        {
          "id": "hqlive-8f0fd3dfa5",
          "name": "Riga vs Rīgas FS | 23:00 17/06",
          "type": "single",
          "display": "thumbnail-only",
          "enable_detail": false,
          "labels": [
            {
              "text": "● LIVE",
              "position": "top-left",
              "color": "#00000080",
              "text_color": "#ff4444"
            }
          ],
          "sources": [
            {
              "id": "src-8f0fd3dfa5",
              "name": "HoiQuanTV",
              "contents": [
                {
                  "id": "ct-8f0fd3dfa5",
                  "name": "Riga vs Rīgas FS",
                  "streams": [
                    {
                      "id": "st-8f0fd3dfa5",
                      "name": "HQ",
                      "stream_links": [
                        {
                          "id": "lnk-1cad2e4412",
                          "name": "BLV TÁO GIÀ",
                          "type": "hls",
                          "default": true,
                          "url": "https://tdlive.yarncdn.live/live/tdtv_blv_taotinhtao/playlist.m3u8",
                          "request_headers": [
                            {
                              "key": "Referer",
                              "value": "https://sv2.hoiquan3.live/"
                            },
                            {
                              "key": "User-Agent",
                              "value": "Mozilla/5.0"
                            }
                          ]
                        }
                      ]
                    }
                  ]
                }
              ]
            }
          ],
          "org_metadata": {
            "league": "Virsliga",
            "team_a": "Riga",
            "team_b": "Rīgas FS",
            "logo_a": "https://media.api-sports.io/football/teams/10124.png",
            "logo_b": "https://media.api-sports.io/football/teams/4160.png",
            "time": "23:00 17/06",
            "blv": "BLV TÁO GIÀ",
            "is_live": true,
            "sport_slug": "bong-da"
          },
          "image": {
            "padding": 1,
            "background_color": "#ffffff",
            "display": "contain",
            "url": "https://raw.githubusercontent.com/jasminliu98/hoiquan-stream/refs/heads/main/thumbs/Riga_Rīgas FS_23-00 17-06_1c53a67b_20260618.png?v=1c53a67b",
            "width": 1600,
            "height": 1200
          }
        },
        {
          "id": "hqlive-2adb270c2f",
          "name": "Portugal vs Congo DR | 00:00 18/06",
          "type": "single",
          "display": "thumbnail-only",
          "enable_detail": false,
          "labels": [
            {
              "text": "● LIVE",
              "position": "top-left",
              "color": "#00000080",
              "text_color": "#ff4444"
            }
          ],
          "sources": [
            {
              "id": "src-2adb270c2f",
              "name": "HoiQuanTV",
              "contents": [
                {
                  "id": "ct-2adb270c2f",
                  "name": "Portugal vs Congo DR",
                  "streams": [
                    {
                      "id": "st-2adb270c2f",
                      "name": "HQ",
                      "stream_links": [
                        {
                          "id": "lnk-c42241b387",
                          "name": "BLV PHAN MÃ",
                          "type": "hls",
                          "default": true,
                          "url": "https://hqlive.yarncdn.live/live/hqtv_blv_phanma/playlist.m3u8",
                          "request_headers": [
                            {
                              "key": "Referer",
                              "value": "https://sv2.hoiquan3.live/"
                            },
                            {
                              "key": "User-Agent",
                              "value": "Mozilla/5.0"
                            }
                          ]
                        },
                        {
                          "id": "lnk-b3ac35be40",
                          "name": "BLV PHAN CHỚP",
                          "type": "hls",
                          "default": false,
                          "url": "https://hqlive.yarncdn.live/live/hqtv_blv_phanchop/playlist.m3u8",
                          "request_headers": [
                            {
                              "key": "Referer",
                              "value": "https://sv2.hoiquan3.live/"
                            },
                            {
                              "key": "User-Agent",
                              "value": "Mozilla/5.0"
                            }
                          ]
                        },
                        {
                          "id": "lnk-b0c182498f",
                          "name": "BLV PHAN QUẨY",
                          "type": "hls",
                          "default": false,
                          "url": "https://hqlive.yarncdn.live/live/hqtv_blv_phanquay/playlist.m3u8",
                          "request_headers": [
                            {
                              "key": "Referer",
                              "value": "https://sv2.hoiquan3.live/"
                            },
                            {
                              "key": "User-Agent",
                              "value": "Mozilla/5.0"
                            }
                          ]
                        }
                      ]
                    }
                  ]
                }
              ]
            }
          ],
          "org_metadata": {
            "league": "World Cup",
            "team_a": "Portugal",
            "team_b": "Congo DR",
            "logo_a": "https://media.api-sports.io/football/teams/27.png",
            "logo_b": "https://upload.wikimedia.org/wikipedia/commons/thumb/6/6f/Flag_of_the_Democratic_Republic_of_the_Congo.svg/1280px-Flag_of_the_Democratic_Republic_of_the_Congo.svg.png",
            "time": "00:00 18/06",
            "blv": "BLV PHAN MÃ, BLV PHAN CHỚP, BLV PHAN QUẨY",
            "is_live": true,
            "sport_slug": "bong-da"
          },
          "image": {
            "padding": 1,
            "background_color": "#ffffff",
            "display": "contain",
            "url": "https://raw.githubusercontent.com/jasminliu98/hoiquan-stream/refs/heads/main/thumbs/Portugal_Congo DR_00-00 18-06_1c9fe960_20260618.png?v=1c9fe960",
            "width": 1600,
            "height": 1200
          }
        },
        {
          "id": "hqlive-6ada8cc05b",
          "name": "Rågsved vs Enköping | 00:30 18/06",
          "type": "single",
          "display": "thumbnail-only",
          "enable_detail": false,
          "labels": [
            {
              "text": "🕐 Sắp",
              "position": "top-left",
              "color": "#00000080",
              "text_color": "#aaaaaa"
            }
          ],
          "sources": [
            {
              "id": "src-6ada8cc05b",
              "name": "HoiQuanTV",
              "contents": [
                {
                  "id": "ct-6ada8cc05b",
                  "name": "Rågsved vs Enköping",
                  "streams": [
                    {
                      "id": "st-6ada8cc05b",
                      "name": "HQ",
                      "stream_links": []
                    }
                  ]
                }
              ]
            }
          ],
          "org_metadata": {
            "league": "Svenska Cupen",
            "team_a": "Rågsved",
            "team_b": "Enköping",
            "logo_a": "https://media.api-sports.io/football/teams/16745.png",
            "logo_b": "https://media.api-sports.io/football/teams/12578.png",
            "time": "00:30 18/06",
            "blv": "BLV TÁO GIÀ",
            "is_live": false,
            "sport_slug": "bong-da"
          },
          "image": {
            "padding": 1,
            "background_color": "#ffffff",
            "display": "contain",
            "url": "https://raw.githubusercontent.com/jasminliu98/hoiquan-stream/refs/heads/main/thumbs/Rågsved_Enköping_00-30 18-06_aa926627_20260618.png?v=aa926627",
            "width": 1600,
            "height": 1200
          }
        },
        {
          "id": "hqlive-f1fa8f8012",
          "name": "England vs Croatia | 03:00 18/06",
          "type": "single",
          "display": "thumbnail-only",
          "enable_detail": false,
          "labels": [
            {
              "text": "🕐 Sắp",
              "position": "top-left",
              "color": "#00000080",
              "text_color": "#aaaaaa"
            }
          ],
          "sources": [
            {
              "id": "src-f1fa8f8012",
              "name": "HoiQuanTV",
              "contents": [
                {
                  "id": "ct-f1fa8f8012",
                  "name": "England vs Croatia",
                  "streams": [
                    {
                      "id": "st-f1fa8f8012",
                      "name": "HQ",
                      "stream_links": []
                    }
                  ]
                }
              ]
            }
          ],
          "org_metadata": {
            "league": "World Cup",
            "team_a": "England",
            "team_b": "Croatia",
            "logo_a": "https://media.api-sports.io/football/teams/10.png",
            "logo_b": "https://upload.wikimedia.org/wikipedia/commons/1/1b/Flag_of_Croatia.svg",
            "time": "03:00 18/06",
            "blv": "BLV PHAN MÃ, BLV PHAN QUẨY, BLV THẦN THÔNG",
            "is_live": false,
            "sport_slug": "bong-da"
          },
          "image": {
            "padding": 1,
            "background_color": "#ffffff",
            "display": "contain",
            "url": "https://raw.githubusercontent.com/jasminliu98/hoiquan-stream/refs/heads/main/thumbs/England_Croatia_03-00 18-06_76127799_20260618.png?v=76127799",
            "width": 1600,
            "height": 1200
          }
        },
        {
          "id": "hqlive-f3e48c6090",
          "name": "Ghana vs Panama | 06:00 18/06",
          "type": "single",
          "display": "thumbnail-only",
          "enable_detail": false,
          "labels": [
            {
              "text": "🕐 Sắp",
              "position": "top-left",
              "color": "#00000080",
              "text_color": "#aaaaaa"
            }
          ],
          "sources": [
            {
              "id": "src-f3e48c6090",
              "name": "HoiQuanTV",
              "contents": [
                {
                  "id": "ct-f3e48c6090",
                  "name": "Ghana vs Panama",
                  "streams": [
                    {
                      "id": "st-f3e48c6090",
                      "name": "HQ",
                      "stream_links": []
                    }
                  ]
                }
              ]
            }
          ],
          "org_metadata": {
            "league": "World Cup",
            "team_a": "Ghana",
            "team_b": "Panama",
            "logo_a": "https://upload.wikimedia.org/wikipedia/commons/1/19/Flag_of_Ghana.svg",
            "logo_b": "https://upload.wikimedia.org/wikipedia/commons/thumb/a/ab/Flag_of_Panama.svg/250px-Flag_of_Panama.svg.png",
            "time": "06:00 18/06",
            "blv": "BLV THẦN THÔNG, BLV LƯƠNG BỔNG",
            "is_live": false,
            "sport_slug": "bong-da"
          },
          "image": {
            "padding": 1,
            "background_color": "#ffffff",
            "display": "contain",
            "url": "https://raw.githubusercontent.com/jasminliu98/hoiquan-stream/refs/heads/main/thumbs/Ghana_Panama_06-00 18-06_3252e6a7_20260618.png?v=3252e6a7",
            "width": 1600,
            "height": 1200
          }
        },
        {
          "id": "hqlive-6fa68ad867",
          "name": "FC Tulsa vs Monterey Bay | 07:30 18/06",
          "type": "single",
          "display": "thumbnail-only",
          "enable_detail": false,
          "labels": [
            {
              "text": "🕐 Sắp",
              "position": "top-left",
              "color": "#00000080",
              "text_color": "#aaaaaa"
            }
          ],
          "sources": [
            {
              "id": "src-6fa68ad867",
              "name": "HoiQuanTV",
              "contents": [
                {
                  "id": "ct-6fa68ad867",
                  "name": "FC Tulsa vs Monterey Bay",
                  "streams": [
                    {
                      "id": "st-6fa68ad867",
                      "name": "HQ",
                      "stream_links": []
                    }
                  ]
                }
              ]
            }
          ],
          "org_metadata": {
            "league": "USL Championship",
            "team_a": "FC Tulsa",
            "team_b": "Monterey Bay",
            "logo_a": "https://media.api-sports.io/football/teams/4022.png",
            "logo_b": "https://media.api-sports.io/football/teams/18375.png",
            "time": "07:30 18/06",
            "blv": "BLV PHAN ANH",
            "is_live": false,
            "sport_slug": "bong-da"
          },
          "image": {
            "padding": 1,
            "background_color": "#ffffff",
            "display": "contain",
            "url": "https://raw.githubusercontent.com/jasminliu98/hoiquan-stream/refs/heads/main/thumbs/FC Tulsa_Monterey Bay_07-30 18-06_5f75a5b4_20260618.png?v=5f75a5b4",
            "width": 1600,
            "height": 1200
          }
        },
        {
          "id": "hqlive-cdc6ccaaac",
          "name": "Uzbekistan vs Colombia | 09:00 18/06",
          "type": "single",
          "display": "thumbnail-only",
          "enable_detail": false,
          "labels": [
            {
              "text": "🕐 Sắp",
              "position": "top-left",
              "color": "#00000080",
              "text_color": "#aaaaaa"
            }
          ],
          "sources": [
            {
              "id": "src-cdc6ccaaac",
              "name": "HoiQuanTV",
              "contents": [
                {
                  "id": "ct-cdc6ccaaac",
                  "name": "Uzbekistan vs Colombia",
                  "streams": [
                    {
                      "id": "st-cdc6ccaaac",
                      "name": "HQ",
                      "stream_links": []
                    }
                  ]
                }
              ]
            }
          ],
          "org_metadata": {
            "league": "World Cup",
            "team_a": "Uzbekistan",
            "team_b": "Colombia",
            "logo_a": "https://media.api-sports.io/football/teams/1568.png",
            "logo_b": "https://upload.wikimedia.org/wikipedia/commons/2/21/Flag_of_Colombia.svg",
            "time": "09:00 18/06",
            "blv": "BLV PHAN QUẨY, BLV LƯƠNG BỔNG",
            "is_live": false,
            "sport_slug": "bong-da"
          },
          "image": {
            "padding": 1,
            "background_color": "#ffffff",
            "display": "contain",
            "url": "https://raw.githubusercontent.com/jasminliu98/hoiquan-stream/refs/heads/main/thumbs/Uzbekistan_Colombia_09-00 18-06_1d6f4741_20260618.png?v=1d6f4741",
            "width": 1600,
            "height": 1200
          }
        },
        {
          "id": "hqlive-b15d654b27",
          "name": "AC Oulu vs Mariehamn | 16:59 18/06",
          "type": "single",
          "display": "thumbnail-only",
          "enable_detail": false,
          "labels": [
            {
              "text": "🕐 Sắp",
              "position": "top-left",
              "color": "#00000080",
              "text_color": "#aaaaaa"
            }
          ],
          "sources": [
            {
              "id": "src-b15d654b27",
              "name": "HoiQuanTV",
              "contents": [
                {
                  "id": "ct-b15d654b27",
                  "name": "AC Oulu vs Mariehamn",
                  "streams": [
                    {
                      "id": "st-b15d654b27",
                      "name": "HQ",
                      "stream_links": []
                    }
                  ]
                }
              ]
            }
          ],
          "org_metadata": {
            "league": "Veikkausliiga",
            "team_a": "AC Oulu",
            "team_b": "Mariehamn",
            "logo_a": "https://media.api-sports.io/football/teams/2077.png",
            "logo_b": "https://media.api-sports.io/football/teams/587.png",
            "time": "16:59 18/06",
            "blv": "BLV PHAN ANH",
            "is_live": false,
            "sport_slug": "bong-da"
          },
          "image": {
            "padding": 1,
            "background_color": "#ffffff",
            "display": "contain",
            "url": "https://raw.githubusercontent.com/jasminliu98/hoiquan-stream/refs/heads/main/thumbs/AC Oulu_Mariehamn_16-59 18-06_d5e03ee2_20260618.png?v=d5e03ee2",
            "width": 1600,
            "height": 1200
          }
        },
        {
          "id": "hqlive-3ba2bb8a5f",
          "name": "Akademiya Ontustik vs Yelimay Semey 2 | 19:00 18/06",
          "type": "single",
          "display": "thumbnail-only",
          "enable_detail": false,
          "labels": [
            {
              "text": "🕐 Sắp",
              "position": "top-left",
              "color": "#00000080",
              "text_color": "#aaaaaa"
            }
          ],
          "sources": [
            {
              "id": "src-3ba2bb8a5f",
              "name": "HoiQuanTV",
              "contents": [
                {
                  "id": "ct-3ba2bb8a5f",
                  "name": "Akademiya Ontustik vs Yelimay Semey 2",
                  "streams": [
                    {
                      "id": "st-3ba2bb8a5f",
                      "name": "HQ",
                      "stream_links": []
                    }
                  ]
                }
              ]
            }
          ],
          "org_metadata": {
            "league": "1. Division",
            "team_a": "Akademiya Ontustik",
            "team_b": "Yelimay Semey 2",
            "logo_a": "https://media.api-sports.io/football/teams/4545.png",
            "logo_b": "https://media.api-sports.io/football/teams/27635.png",
            "time": "19:00 18/06",
            "blv": "BLV TÁO GIÀ",
            "is_live": false,
            "sport_slug": "bong-da"
          },
          "image": {
            "padding": 1,
            "background_color": "#ffffff",
            "display": "contain",
            "url": "https://raw.githubusercontent.com/jasminliu98/hoiquan-stream/refs/heads/main/thumbs/Akademiya Ontustik_Yelimay Semey 2_19-00 18-06_2214b6e8_20260618.png?v=2214b6e8",
            "width": 1600,
            "height": 1200
          }
        },
        {
          "id": "hqlive-2e52cce8fe",
          "name": "Arys vs Kaspij Aktau 2 | 20:00 18/06",
          "type": "single",
          "display": "thumbnail-only",
          "enable_detail": false,
          "labels": [
            {
              "text": "🕐 Sắp",
              "position": "top-left",
              "color": "#00000080",
              "text_color": "#aaaaaa"
            }
          ],
          "sources": [
            {
              "id": "src-2e52cce8fe",
              "name": "HoiQuanTV",
              "contents": [
                {
                  "id": "ct-2e52cce8fe",
                  "name": "Arys vs Kaspij Aktau 2",
                  "streams": [
                    {
                      "id": "st-2e52cce8fe",
                      "name": "HQ",
                      "stream_links": []
                    }
                  ]
                }
              ]
            }
          ],
          "org_metadata": {
            "league": "1. Division",
            "team_a": "Arys",
            "team_b": "Kaspij Aktau 2",
            "logo_a": "https://media.api-sports.io/football/teams/10414.png",
            "logo_b": "https://media.api-sports.io/football/teams/27633.png",
            "time": "20:00 18/06",
            "blv": "BLV PHAN ANH",
            "is_live": false,
            "sport_slug": "bong-da"
          },
          "image": {
            "padding": 1,
            "background_color": "#ffffff",
            "display": "contain",
            "url": "https://raw.githubusercontent.com/jasminliu98/hoiquan-stream/refs/heads/main/thumbs/Arys_Kaspij Aktau 2_20-00 18-06_342f0ba5_20260618.png?v=342f0ba5",
            "width": 1600,
            "height": 1200
          }
        },
        {
          "id": "hqlive-a665e666d9",
          "name": "Turan Turkistan vs Aktobe Jas | 22:00 18/06",
          "type": "single",
          "display": "thumbnail-only",
          "enable_detail": false,
          "labels": [
            {
              "text": "🕐 Sắp",
              "position": "top-left",
              "color": "#00000080",
              "text_color": "#aaaaaa"
            }
          ],
          "sources": [
            {
              "id": "src-a665e666d9",
              "name": "HoiQuanTV",
              "contents": [
                {
                  "id": "ct-a665e666d9",
                  "name": "Turan Turkistan vs Aktobe Jas",
                  "streams": [
                    {
                      "id": "st-a665e666d9",
                      "name": "HQ",
                      "stream_links": []
                    }
                  ]
                }
              ]
            }
          ],
          "org_metadata": {
            "league": "1. Division",
            "team_a": "Turan Turkistan",
            "team_b": "Aktobe Jas",
            "logo_a": "https://media.api-sports.io/football/teams/21502.png",
            "logo_b": "https://media.api-sports.io/football/teams/4546.png",
            "time": "22:00 18/06",
            "blv": "BLV TÁO GIÀ",
            "is_live": false,
            "sport_slug": "bong-da"
          },
          "image": {
            "padding": 1,
            "background_color": "#ffffff",
            "display": "contain",
            "url": "https://raw.githubusercontent.com/jasminliu98/hoiquan-stream/refs/heads/main/thumbs/Turan Turkistan_Aktobe Jas_22-00 18-06_c18d8bb8_20260618.png?v=c18d8bb8",
            "width": 1600,
            "height": 1200
          }
        },
        {
          "id": "hqlive-ae0fc882ed",
          "name": "Czech Republic vs South Africa | 23:00 18/06",
          "type": "single",
          "display": "thumbnail-only",
          "enable_detail": false,
          "labels": [
            {
              "text": "🕐 Sắp",
              "position": "top-left",
              "color": "#00000080",
              "text_color": "#aaaaaa"
            }
          ],
          "sources": [
            {
              "id": "src-ae0fc882ed",
              "name": "HoiQuanTV",
              "contents": [
                {
                  "id": "ct-ae0fc882ed",
                  "name": "Czech Republic vs South Africa",
                  "streams": [
                    {
                      "id": "st-ae0fc882ed",
                      "name": "HQ",
                      "stream_links": []
                    }
                  ]
                }
              ]
            }
          ],
          "org_metadata": {
            "league": "World Cup",
            "team_a": "Czech Republic",
            "team_b": "South Africa",
            "logo_a": "https://media.api-sports.io/football/teams/770.png",
            "logo_b": "https://upload.wikimedia.org/wikipedia/commons/thumb/a/af/Flag_of_South_Africa.svg/1280px-Flag_of_South_Africa.svg.png",
            "time": "23:00 18/06",
            "blv": "BLV PHAN MÃ, BLV PHAN CHỚP",
            "is_live": false,
            "sport_slug": "bong-da"
          },
          "image": {
            "padding": 1,
            "background_color": "#ffffff",
            "display": "contain",
            "url": "https://raw.githubusercontent.com/jasminliu98/hoiquan-stream/refs/heads/main/thumbs/Czech Republic_South Africa_23-00 18-06_5de77a66_20260618.png?v=5de77a66",
            "width": 1600,
            "height": 1200
          }
        }
      ]
    },
    {
      "id": "sport_bong-chuyen",
      "name": "🏐 Bóng Chuyền (1 LIVE)",
      "display": "vertical",
      "grid_number": 2,
      "enable_detail": false,
      "channels": [
        {
          "id": "hqlive-7c9424220a",
          "name": "Thổ Nhĩ Kỳ vs Bỉ | 23:30 17/06",
          "type": "single",
          "display": "thumbnail-only",
          "enable_detail": false,
          "labels": [
            {
              "text": "● LIVE",
              "position": "top-left",
              "color": "#00000080",
              "text_color": "#ff4444"
            }
          ],
          "sources": [
            {
              "id": "src-7c9424220a",
              "name": "HoiQuanTV",
              "contents": [
                {
                  "id": "ct-7c9424220a",
                  "name": "Thổ Nhĩ Kỳ vs Bỉ",
                  "streams": [
                    {
                      "id": "st-7c9424220a",
                      "name": "HQ",
                      "stream_links": [
                        {
                          "id": "lnk-6568b58b01",
                          "name": "BLV PHAN BỐNG",
                          "type": "hls",
                          "default": true,
                          "url": "https://hqlive.yarncdn.live/live/hqtv_blv_phanbong/playlist.m3u8",
                          "request_headers": [
                            {
                              "key": "Referer",
                              "value": "https://sv2.hoiquan3.live/"
                            },
                            {
                              "key": "User-Agent",
                              "value": "Mozilla/5.0"
                            }
                          ]
                        }
                      ]
                    }
                  ]
                }
              ]
            }
          ],
          "org_metadata": {
            "league": "Nation League Women",
            "team_a": "Thổ Nhĩ Kỳ",
            "team_b": "Bỉ",
            "logo_a": "https://upload.wikimedia.org/wikipedia/commons/b/b4/Flag_of_Turkey.svg",
            "logo_b": "https://upload.wikimedia.org/wikipedia/commons/thumb/6/65/Flag_of_Belgium.svg/250px-Flag_of_Belgium.svg.png",
            "time": "23:30 17/06",
            "blv": "BLV PHAN BỐNG",
            "is_live": true,
            "sport_slug": "bong-chuyen"
          },
          "image": {
            "padding": 1,
            "background_color": "#ffffff",
            "display": "contain",
            "url": "https://raw.githubusercontent.com/jasminliu98/hoiquan-stream/refs/heads/main/thumbs/Thổ Nhĩ Kỳ_Bỉ_23-30 17-06_9f81e585_20260618.png?v=9f81e585",
            "width": 1600,
            "height": 1200
          }
        },
        {
          "id": "hqlive-6f6b872fc6",
          "name": "CH Séc vs Mỹ | 15:00 18/06",
          "type": "single",
          "display": "thumbnail-only",
          "enable_detail": false,
          "labels": [
            {
              "text": "🕐 Sắp",
              "position": "top-left",
              "color": "#00000080",
              "text_color": "#aaaaaa"
            }
          ],
          "sources": [
            {
              "id": "src-6f6b872fc6",
              "name": "HoiQuanTV",
              "contents": [
                {
                  "id": "ct-6f6b872fc6",
                  "name": "CH Séc vs Mỹ",
                  "streams": [
                    {
                      "id": "st-6f6b872fc6",
                      "name": "HQ",
                      "stream_links": []
                    }
                  ]
                }
              ]
            }
          ],
          "org_metadata": {
            "league": "Nation League Women",
            "team_a": "CH Séc",
            "team_b": "Mỹ",
            "logo_a": "https://upload.wikimedia.org/wikipedia/commons/c/cb/Flag_of_the_Czech_Republic.svg",
            "logo_b": "https://www.englisch-hilfen.de/images/flags/248.gif",
            "time": "15:00 18/06",
            "blv": "BLV TÁO GIÀ",
            "is_live": false,
            "sport_slug": "bong-chuyen"
          },
          "image": {
            "padding": 1,
            "background_color": "#ffffff",
            "display": "contain",
            "url": "https://raw.githubusercontent.com/jasminliu98/hoiquan-stream/refs/heads/main/thumbs/CH Séc_Mỹ_15-00 18-06_e435fa29_20260618.png?v=e435fa29",
            "width": 1600,
            "height": 1200
          }
        },
        {
          "id": "hqlive-d91800ed2e",
          "name": "Ukraina vs Ba Lan | 17:00 18/06",
          "type": "single",
          "display": "thumbnail-only",
          "enable_detail": false,
          "labels": [
            {
              "text": "🕐 Sắp",
              "position": "top-left",
              "color": "#00000080",
              "text_color": "#aaaaaa"
            }
          ],
          "sources": [
            {
              "id": "src-d91800ed2e",
              "name": "HoiQuanTV",
              "contents": [
                {
                  "id": "ct-d91800ed2e",
                  "name": "Ukraina vs Ba Lan",
                  "streams": [
                    {
                      "id": "st-d91800ed2e",
                      "name": "HQ",
                      "stream_links": []
                    }
                  ]
                }
              ]
            }
          ],
          "org_metadata": {
            "league": "Nation League Women",
            "team_a": "Ukraina",
            "team_b": "Ba Lan",
            "logo_a": "https://upload.wikimedia.org/wikipedia/commons/4/49/Flag_of_Ukraine.svg",
            "logo_b": "https://encrypted-tbn0.gstatic.com/images?q=tbn:ANd9GcTxLkHp8_KNZVw1jCYb3bu1mvTTOxYcnl5yQQ&s",
            "time": "17:00 18/06",
            "blv": "BLV PHAN BỐNG",
            "is_live": false,
            "sport_slug": "bong-chuyen"
          },
          "image": {
            "padding": 1,
            "background_color": "#ffffff",
            "display": "contain",
            "url": "https://raw.githubusercontent.com/jasminliu98/hoiquan-stream/refs/heads/main/thumbs/Ukraina_Ba Lan_17-00 18-06_6595f1d1_20260618.png?v=6595f1d1",
            "width": 1600,
            "height": 1200
          }
        },
        {
          "id": "hqlive-f936e7ff1e",
          "name": "Serbia vs Italy | 19:00 18/06",
          "type": "single",
          "display": "thumbnail-only",
          "enable_detail": false,
          "labels": [
            {
              "text": "🕐 Sắp",
              "position": "top-left",
              "color": "#00000080",
              "text_color": "#aaaaaa"
            }
          ],
          "sources": [
            {
              "id": "src-f936e7ff1e",
              "name": "HoiQuanTV",
              "contents": [
                {
                  "id": "ct-f936e7ff1e",
                  "name": "Serbia vs Italy",
                  "streams": [
                    {
                      "id": "st-f936e7ff1e",
                      "name": "HQ",
                      "stream_links": []
                    }
                  ]
                }
              ]
            }
          ],
          "org_metadata": {
            "league": "Nation League Women",
            "team_a": "Serbia",
            "team_b": "Italy",
            "logo_a": "https://upload.wikimedia.org/wikipedia/commons/thumb/f/ff/Flag_of_Serbia.svg/250px-Flag_of_Serbia.svg.png",
            "logo_b": "https://upload.wikimedia.org/wikipedia/commons/0/03/Flag_of_Italy.svg",
            "time": "19:00 18/06",
            "blv": "BLV LƯƠNG BỔNG",
            "is_live": false,
            "sport_slug": "bong-chuyen"
          },
          "image": {
            "padding": 1,
            "background_color": "#ffffff",
            "display": "contain",
            "url": "https://raw.githubusercontent.com/jasminliu98/hoiquan-stream/refs/heads/main/thumbs/Serbia_Italy_19-00 18-06_bfa6411f_20260618.png?v=bfa6411f",
            "width": 1600,
            "height": 1200
          }
        },
        {
          "id": "hqlive-4199e86878",
          "name": "Bỉ vs Brazil | 20:00 18/06",
          "type": "single",
          "display": "thumbnail-only",
          "enable_detail": false,
          "labels": [
            {
              "text": "🕐 Sắp",
              "position": "top-left",
              "color": "#00000080",
              "text_color": "#aaaaaa"
            }
          ],
          "sources": [
            {
              "id": "src-4199e86878",
              "name": "HoiQuanTV",
              "contents": [
                {
                  "id": "ct-4199e86878",
                  "name": "Bỉ vs Brazil",
                  "streams": [
                    {
                      "id": "st-4199e86878",
                      "name": "HQ",
                      "stream_links": []
                    }
                  ]
                }
              ]
            }
          ],
          "org_metadata": {
            "league": "Nation League Women",
            "team_a": "Bỉ",
            "team_b": "Brazil",
            "logo_a": "https://upload.wikimedia.org/wikipedia/commons/thumb/6/65/Flag_of_Belgium.svg/250px-Flag_of_Belgium.svg.png",
            "logo_b": "https://upload.wikimedia.org/wikipedia/commons/thumb/2/2e/Flag_of_Brazil_%281968%E2%80%931992%29.svg/250px-Flag_of_Brazil_%281968%E2%80%931992%29.svg.png",
            "time": "20:00 18/06",
            "blv": "BLV PHAN BỐNG",
            "is_live": false,
            "sport_slug": "bong-chuyen"
          },
          "image": {
            "padding": 1,
            "background_color": "#ffffff",
            "display": "contain",
            "url": "https://raw.githubusercontent.com/jasminliu98/hoiquan-stream/refs/heads/main/thumbs/Bỉ_Brazil_20-00 18-06_3c520c75_20260618.png?v=3c520c75",
            "width": 1600,
            "height": 1200
          }
        },
        {
          "id": "hqlive-2acbe375e5",
          "name": "Thái Lan vs Bulgaria | 20:30 18/06",
          "type": "single",
          "display": "thumbnail-only",
          "enable_detail": false,
          "labels": [
            {
              "text": "🕐 Sắp",
              "position": "top-left",
              "color": "#00000080",
              "text_color": "#aaaaaa"
            }
          ],
          "sources": [
            {
              "id": "src-2acbe375e5",
              "name": "HoiQuanTV",
              "contents": [
                {
                  "id": "ct-2acbe375e5",
                  "name": "Thái Lan vs Bulgaria",
                  "streams": [
                    {
                      "id": "st-2acbe375e5",
                      "name": "HQ",
                      "stream_links": []
                    }
                  ]
                }
              ]
            }
          ],
          "org_metadata": {
            "league": "Nation League Women",
            "team_a": "Thái Lan",
            "team_b": "Bulgaria",
            "logo_a": "https://upload.wikimedia.org/wikipedia/commons/a/a9/Flag_of_Thailand.svg",
            "logo_b": "https://upload.wikimedia.org/wikipedia/commons/thumb/9/9a/Flag_of_Bulgaria.svg/250px-Flag_of_Bulgaria.svg.png",
            "time": "20:30 18/06",
            "blv": "BLV PHAN PHÉP",
            "is_live": false,
            "sport_slug": "bong-chuyen"
          },
          "image": {
            "padding": 1,
            "background_color": "#ffffff",
            "display": "contain",
            "url": "https://raw.githubusercontent.com/jasminliu98/hoiquan-stream/refs/heads/main/thumbs/Thái Lan_Bulgaria_20-30 18-06_d550e52e_20260618.png?v=d550e52e",
            "width": 1600,
            "height": 1200
          }
        },
        {
          "id": "hqlive-dbffecf38e",
          "name": "Thổ Nhĩ Kỳ vs Pháp | 23:30 18/06",
          "type": "single",
          "display": "thumbnail-only",
          "enable_detail": false,
          "labels": [
            {
              "text": "🕐 Sắp",
              "position": "top-left",
              "color": "#00000080",
              "text_color": "#aaaaaa"
            }
          ],
          "sources": [
            {
              "id": "src-dbffecf38e",
              "name": "HoiQuanTV",
              "contents": [
                {
                  "id": "ct-dbffecf38e",
                  "name": "Thổ Nhĩ Kỳ vs Pháp",
                  "streams": [
                    {
                      "id": "st-dbffecf38e",
                      "name": "HQ",
                      "stream_links": []
                    }
                  ]
                }
              ]
            }
          ],
          "org_metadata": {
            "league": "Nation League Women",
            "team_a": "Thổ Nhĩ Kỳ",
            "team_b": "Pháp",
            "logo_a": "https://upload.wikimedia.org/wikipedia/commons/b/b4/Flag_of_Turkey.svg",
            "logo_b": "https://upload.wikimedia.org/wikipedia/commons/thumb/3/3f/Ensign_of_France.svg/250px-Ensign_of_France.svg.png",
            "time": "23:30 18/06",
            "blv": "BLV LƯƠNG BỔNG",
            "is_live": false,
            "sport_slug": "bong-chuyen"
          },
          "image": {
            "padding": 1,
            "background_color": "#ffffff",
            "display": "contain",
            "url": "https://raw.githubusercontent.com/jasminliu98/hoiquan-stream/refs/heads/main/thumbs/Thổ Nhĩ Kỳ_Pháp_23-30 18-06_2dff64f3_20260618.png?v=2dff64f3",
            "width": 1600,
            "height": 1200
          }
        },
        {
          "id": "hqlive-09da3d9315",
          "name": "Cộng Hòa Dominicana vs Serbia | 15:00 19/06",
          "type": "single",
          "display": "thumbnail-only",
          "enable_detail": false,
          "labels": [
            {
              "text": "🕐 Sắp",
              "position": "top-left",
              "color": "#00000080",
              "text_color": "#aaaaaa"
            }
          ],
          "sources": [
            {
              "id": "src-09da3d9315",
              "name": "HoiQuanTV",
              "contents": [
                {
                  "id": "ct-09da3d9315",
                  "name": "Cộng Hòa Dominicana vs Serbia",
                  "streams": [
                    {
                      "id": "st-09da3d9315",
                      "name": "HQ",
                      "stream_links": []
                    }
                  ]
                }
              ]
            }
          ],
          "org_metadata": {
            "league": "Nation League Women",
            "team_a": "Cộng Hòa Dominicana",
            "team_b": "Serbia",
            "logo_a": "https://upload.wikimedia.org/wikipedia/commons/9/9f/Flag_of_the_Dominican_Republic.svg",
            "logo_b": "https://upload.wikimedia.org/wikipedia/commons/thumb/f/ff/Flag_of_Serbia.svg/250px-Flag_of_Serbia.svg.png",
            "time": "15:00 19/06",
            "blv": "BLV PHAN HẢI",
            "is_live": false,
            "sport_slug": "bong-chuyen"
          },
          "image": {
            "padding": 1,
            "background_color": "#ffffff",
            "display": "contain",
            "url": "https://raw.githubusercontent.com/jasminliu98/hoiquan-stream/refs/heads/main/thumbs/Cộng Hòa Dominicana_Serbia_15-00 19-06_b71a832e_20260618.png?v=b71a832e",
            "width": 1600,
            "height": 1200
          }
        },
        {
          "id": "hqlive-52d96b420d",
          "name": "Ukraina vs Hà Lan | 17:00 19/06",
          "type": "single",
          "display": "thumbnail-only",
          "enable_detail": false,
          "labels": [
            {
              "text": "🕐 Sắp",
              "position": "top-left",
              "color": "#00000080",
              "text_color": "#aaaaaa"
            }
          ],
          "sources": [
            {
              "id": "src-52d96b420d",
              "name": "HoiQuanTV",
              "contents": [
                {
                  "id": "ct-52d96b420d",
                  "name": "Ukraina vs Hà Lan",
                  "streams": [
                    {
                      "id": "st-52d96b420d",
                      "name": "HQ",
                      "stream_links": []
                    }
                  ]
                }
              ]
            }
          ],
          "org_metadata": {
            "league": "Nation League Women",
            "team_a": "Ukraina",
            "team_b": "Hà Lan",
            "logo_a": "https://upload.wikimedia.org/wikipedia/commons/4/49/Flag_of_Ukraine.svg",
            "logo_b": "https://upload.wikimedia.org/wikipedia/commons/2/20/Flag_of_the_Netherlands.svg",
            "time": "17:00 19/06",
            "blv": "BLV PHAN BỐNG",
            "is_live": false,
            "sport_slug": "bong-chuyen"
          },
          "image": {
            "padding": 1,
            "background_color": "#ffffff",
            "display": "contain",
            "url": "https://raw.githubusercontent.com/jasminliu98/hoiquan-stream/refs/heads/main/thumbs/Ukraina_Hà Lan_17-00 19-06_8be663c0_20260618.png?v=8be663c0",
            "width": 1600,
            "height": 1200
          }
        },
        {
          "id": "hqlive-92b031c422",
          "name": "Nhật Bản vs CH Séc | 19:00 19/06",
          "type": "single",
          "display": "thumbnail-only",
          "enable_detail": false,
          "labels": [
            {
              "text": "🕐 Sắp",
              "position": "top-left",
              "color": "#00000080",
              "text_color": "#aaaaaa"
            }
          ],
          "sources": [
            {
              "id": "src-92b031c422",
              "name": "HoiQuanTV",
              "contents": [
                {
                  "id": "ct-92b031c422",
                  "name": "Nhật Bản vs CH Séc",
                  "streams": [
                    {
                      "id": "st-92b031c422",
                      "name": "HQ",
                      "stream_links": []
                    }
                  ]
                }
              ]
            }
          ],
          "org_metadata": {
            "league": "Nation League Women",
            "team_a": "Nhật Bản",
            "team_b": "CH Séc",
            "logo_a": "https://upload.wikimedia.org/wikipedia/commons/thumb/9/9e/Flag_of_Japan.svg/960px-Flag_of_Japan.svg.png",
            "logo_b": "https://upload.wikimedia.org/wikipedia/commons/c/cb/Flag_of_the_Czech_Republic.svg",
            "time": "19:00 19/06",
            "blv": "BLV LƯƠNG BỔNG",
            "is_live": false,
            "sport_slug": "bong-chuyen"
          },
          "image": {
            "padding": 1,
            "background_color": "#ffffff",
            "display": "contain",
            "url": "https://raw.githubusercontent.com/jasminliu98/hoiquan-stream/refs/heads/main/thumbs/Nhật Bản_CH Séc_19-00 19-06_e97304a8_20260618.png?v=e97304a8",
            "width": 1600,
            "height": 1200
          }
        },
        {
          "id": "hqlive-275e338825",
          "name": "Pháp vs Trung Quốc | 20:00 19/06",
          "type": "single",
          "display": "thumbnail-only",
          "enable_detail": false,
          "labels": [
            {
              "text": "🕐 Sắp",
              "position": "top-left",
              "color": "#00000080",
              "text_color": "#aaaaaa"
            }
          ],
          "sources": [
            {
              "id": "src-275e338825",
              "name": "HoiQuanTV",
              "contents": [
                {
                  "id": "ct-275e338825",
                  "name": "Pháp vs Trung Quốc",
                  "streams": [
                    {
                      "id": "st-275e338825",
                      "name": "HQ",
                      "stream_links": []
                    }
                  ]
                }
              ]
            }
          ],
          "org_metadata": {
            "league": "Nation League Women",
            "team_a": "Pháp",
            "team_b": "Trung Quốc",
            "logo_a": "https://upload.wikimedia.org/wikipedia/commons/thumb/3/3f/Ensign_of_France.svg/250px-Ensign_of_France.svg.png",
            "logo_b": "https://encrypted-tbn0.gstatic.com/images?q=tbn:ANd9GcRZQOuJBhheUKikHwopx5J3hD7olyljs3suGQ&s",
            "time": "20:00 19/06",
            "blv": "BLV PHAN HẢI",
            "is_live": false,
            "sport_slug": "bong-chuyen"
          },
          "image": {
            "padding": 1,
            "background_color": "#ffffff",
            "display": "contain",
            "url": "https://raw.githubusercontent.com/jasminliu98/hoiquan-stream/refs/heads/main/thumbs/Pháp_Trung Quốc_20-00 19-06_79fbe832_20260618.png?v=79fbe832",
            "width": 1600,
            "height": 1200
          }
        },
        {
          "id": "hqlive-49aff69c91",
          "name": "Bulgaria vs Canada | 20:30 19/06",
          "type": "single",
          "display": "thumbnail-only",
          "enable_detail": false,
          "labels": [
            {
              "text": "🕐 Sắp",
              "position": "top-left",
              "color": "#00000080",
              "text_color": "#aaaaaa"
            }
          ],
          "sources": [
            {
              "id": "src-49aff69c91",
              "name": "HoiQuanTV",
              "contents": [
                {
                  "id": "ct-49aff69c91",
                  "name": "Bulgaria vs Canada",
                  "streams": [
                    {
                      "id": "st-49aff69c91",
                      "name": "HQ",
                      "stream_links": []
                    }
                  ]
                }
              ]
            }
          ],
          "org_metadata": {
            "league": "Nation League Women",
            "team_a": "Bulgaria",
            "team_b": "Canada",
            "logo_a": "https://upload.wikimedia.org/wikipedia/commons/thumb/9/9a/Flag_of_Bulgaria.svg/250px-Flag_of_Bulgaria.svg.png",
            "logo_b": "https://upload.wikimedia.org/wikipedia/commons/c/cf/Flag_of_Canada.svg",
            "time": "20:30 19/06",
            "blv": "BLV PHAN BỐNG",
            "is_live": false,
            "sport_slug": "bong-chuyen"
          },
          "image": {
            "padding": 1,
            "background_color": "#ffffff",
            "display": "contain",
            "url": "https://raw.githubusercontent.com/jasminliu98/hoiquan-stream/refs/heads/main/thumbs/Bulgaria_Canada_20-30 19-06_a238368e_20260618.png?v=a238368e",
            "width": 1600,
            "height": 1200
          }
        },
        {
          "id": "hqlive-b46062c541",
          "name": "Bỉ vs Đức | 20:30 19/06",
          "type": "single",
          "display": "thumbnail-only",
          "enable_detail": false,
          "labels": [
            {
              "text": "🕐 Sắp",
              "position": "top-left",
              "color": "#00000080",
              "text_color": "#aaaaaa"
            }
          ],
          "sources": [
            {
              "id": "src-b46062c541",
              "name": "HoiQuanTV",
              "contents": [
                {
                  "id": "ct-b46062c541",
                  "name": "Bỉ vs Đức",
                  "streams": [
                    {
                      "id": "st-b46062c541",
                      "name": "HQ",
                      "stream_links": []
                    }
                  ]
                }
              ]
            }
          ],
          "org_metadata": {
            "league": "Nation League Women",
            "team_a": "Bỉ",
            "team_b": "Đức",
            "logo_a": "https://upload.wikimedia.org/wikipedia/commons/thumb/6/65/Flag_of_Belgium.svg/250px-Flag_of_Belgium.svg.png",
            "logo_b": "https://upload.wikimedia.org/wikipedia/commons/thumb/b/ba/Flag_of_Germany.svg/250px-Flag_of_Germany.svg.png",
            "time": "20:30 19/06",
            "blv": "BLV PHAN CHỚP",
            "is_live": false,
            "sport_slug": "bong-chuyen"
          },
          "image": {
            "padding": 1,
            "background_color": "#ffffff",
            "display": "contain",
            "url": "https://raw.githubusercontent.com/jasminliu98/hoiquan-stream/refs/heads/main/thumbs/Bỉ_Đức_20-30 19-06_c8ac3771_20260618.png?v=c8ac3771",
            "width": 1600,
            "height": 1200
          }
        }
      ]
    },
    {
      "id": "sport_tennis",
      "name": "🎾 Tennis (1 LIVE)",
      "display": "vertical",
      "grid_number": 2,
      "enable_detail": false,
      "channels": [
        {
          "id": "hqlive-55e6b6011b",
          "name": "Terence Atmane vs Daniil Medvedev | 22:30 17/06",
          "type": "single",
          "display": "thumbnail-only",
          "enable_detail": false,
          "labels": [
            {
              "text": "● LIVE",
              "position": "top-left",
              "color": "#00000080",
              "text_color": "#ff4444"
            }
          ],
          "sources": [
            {
              "id": "src-55e6b6011b",
              "name": "HoiQuanTV",
              "contents": [
                {
                  "id": "ct-55e6b6011b",
                  "name": "Terence Atmane vs Daniil Medvedev",
                  "streams": [
                    {
                      "id": "st-55e6b6011b",
                      "name": "HQ",
                      "stream_links": [
                        {
                          "id": "lnk-eae8482cb7",
                          "name": "BLV PHAN BÁCH",
                          "type": "hls",
                          "default": true,
                          "url": "https://hqlive.yarncdn.live/live/hqtv_blv_phanchuot/playlist.m3u8",
                          "request_headers": [
                            {
                              "key": "Referer",
                              "value": "https://sv2.hoiquan3.live/"
                            },
                            {
                              "key": "User-Agent",
                              "value": "Mozilla/5.0"
                            }
                          ]
                        }
                      ]
                    }
                  ]
                }
              ]
            }
          ],
          "org_metadata": {
            "league": "ATP500 Halle",
            "team_a": "Terence Atmane",
            "team_b": "Daniil Medvedev",
            "logo_a": "https://image.sggp.org.vn/w1000/Uploaded/2026/ldfnyrykxq/2025_08_15/atmane-5203-3906.jpeg.webp",
            "logo_b": "https://encrypted-tbn0.gstatic.com/images?q=tbn:ANd9GcRU-ThUSVRA1sgqwj_Qe4f22lmchMKp66MuBg&s",
            "time": "22:30 17/06",
            "blv": "BLV PHAN BÁCH",
            "is_live": true,
            "sport_slug": "tennis"
          },
          "image": {
            "padding": 1,
            "background_color": "#ffffff",
            "display": "contain",
            "url": "https://raw.githubusercontent.com/jasminliu98/hoiquan-stream/refs/heads/main/thumbs/Terence Atmane_Daniil Medvedev_22-30 17-06_89f9ec11_20260618.png?v=89f9ec11",
            "width": 1600,
            "height": 1200
          }
        }
      ]
    }
  ]
}