{
  "id": "hoiquan",
  "url": "https://sv2.hoiquan3.live",
  "name": "HoiQuanTV",
  "color": "#1cb57a",
  "updated_at": "20:50 27/05/2026",
  "grid_number": 3,
  "image": {
    "type": "cover",
    "url": "https://sv2.hoiquan3.live/logo.png"
  },
  "groups": [
    {
      "id": "sport_bong-da",
      "name": "⚽ Bóng Đá (2 LIVE)",
      "display": "vertical",
      "grid_number": 2,
      "enable_detail": false,
      "channels": [
        {
          "id": "hqlive-abaf602bc1",
          "name": "Hà Nội Nữ vs Nữ Hồ Chí Minh | 19:00 27/05",
          "type": "single",
          "display": "thumbnail-only",
          "enable_detail": false,
          "labels": [
            {
              "text": "● LIVE",
              "position": "top-left",
              "color": "#00000080",
              "text_color": "#ff4444"
            }
          ],
          "sources": [
            {
              "id": "src-abaf602bc1",
              "name": "HoiQuanTV",
              "contents": [
                {
                  "id": "ct-abaf602bc1",
                  "name": "Hà Nội Nữ vs Nữ Hồ Chí Minh",
                  "streams": [
                    {
                      "id": "st-abaf602bc1",
                      "name": "HQ",
                      "stream_links": [
                        {
                          "id": "lnk-1cad2e4412",
                          "name": "BLV TÁO GIÀ",
                          "type": "hls",
                          "default": true,
                          "url": "https://tdlive.yarncdn.live/live/tdtv_blv_taotinhtao/playlist.m3u8",
                          "request_headers": [
                            {
                              "key": "Referer",
                              "value": "https://sv2.hoiquan3.live/"
                            },
                            {
                              "key": "User-Agent",
                              "value": "Mozilla/5.0"
                            }
                          ]
                        }
                      ]
                    }
                  ]
                }
              ]
            }
          ],
          "org_metadata": {
            "league": "Cúp quốc gia Việt Nam",
            "team_a": "Hà Nội Nữ",
            "team_b": "Nữ Hồ Chí Minh",
            "logo_a": "https://encrypted-tbn0.gstatic.com/images?q=tbn:ANd9GcSrwbRVnSljHy8WGaU8UVE_bNbA_ouun6OHpw&s",
            "logo_b": "https://upload.wikimedia.org/wikipedia/vi/thumb/9/9a/Logo_HWFC.png/250px-Logo_HWFC.png",
            "time": "19:00 27/05",
            "blv": "BLV TÁO GIÀ",
            "is_live": true,
            "sport_slug": "bong-da"
          },
          "image": {
            "padding": 1,
            "background_color": "#ffffff",
            "display": "contain",
            "url": "https://raw.githubusercontent.com/jasminliu98/hoiquan-stream/refs/heads/main/thumbs/Hà Nội Nữ_Nữ Hồ Chí Minh_19-00 27-05_9d3d4587_20260527.png?v=9d3d4587",
            "width": 1600,
            "height": 1200
          }
        },
        {
          "id": "hqlive-05d28f7580",
          "name": "Buriram United vs Selangor | 19:00 27/05",
          "type": "single",
          "display": "thumbnail-only",
          "enable_detail": false,
          "labels": [
            {
              "text": "● LIVE",
              "position": "top-left",
              "color": "#00000080",
              "text_color": "#ff4444"
            }
          ],
          "sources": [
            {
              "id": "src-05d28f7580",
              "name": "HoiQuanTV",
              "contents": [
                {
                  "id": "ct-05d28f7580",
                  "name": "Buriram United vs Selangor",
                  "streams": [
                    {
                      "id": "st-05d28f7580",
                      "name": "HQ",
                      "stream_links": [
                        {
                          "id": "lnk-b10e5b640b",
                          "name": "BLV THẦN THÔNG",
                          "type": "hls",
                          "default": true,
                          "url": "https://tdlive.yarncdn.live/live/tdtv_blv_taovannghe/playlist.m3u8",
                          "request_headers": [
                            {
                              "key": "Referer",
                              "value": "https://sv2.hoiquan3.live/"
                            },
                            {
                              "key": "User-Agent",
                              "value": "Mozilla/5.0"
                            }
                          ]
                        }
                      ]
                    }
                  ]
                }
              ]
            }
          ],
          "org_metadata": {
            "league": "ASEAN Club Championship",
            "team_a": "Buriram United",
            "team_b": "Selangor",
            "logo_a": "https://upload.wikimedia.org/wikipedia/en/thumb/9/93/Buriram_United_logo.svg/250px-Buriram_United_logo.svg.png",
            "logo_b": "https://upload.wikimedia.org/wikipedia/en/d/d7/Selangor_FC_logo.svg",
            "time": "19:00 27/05",
            "blv": "BLV THẦN THÔNG",
            "is_live": true,
            "sport_slug": "bong-da"
          },
          "image": {
            "padding": 1,
            "background_color": "#ffffff",
            "display": "contain",
            "url": "https://raw.githubusercontent.com/jasminliu98/hoiquan-stream/refs/heads/main/thumbs/Buriram United_Selangor_19-00 27-05_c14a1d60_20260527.png?v=c14a1d60",
            "width": 1600,
            "height": 1200
          }
        },
        {
          "id": "hqlive-bf934bcc54",
          "name": "Ararat-Armenia vs Gandzasar | 22:00 27/05",
          "type": "single",
          "display": "thumbnail-only",
          "enable_detail": false,
          "labels": [
            {
              "text": "🕐 Sắp",
              "position": "top-left",
              "color": "#00000080",
              "text_color": "#aaaaaa"
            }
          ],
          "sources": [
            {
              "id": "src-bf934bcc54",
              "name": "HoiQuanTV",
              "contents": [
                {
                  "id": "ct-bf934bcc54",
                  "name": "Ararat-Armenia vs Gandzasar",
                  "streams": [
                    {
                      "id": "st-bf934bcc54",
                      "name": "HQ",
                      "stream_links": []
                    }
                  ]
                }
              ]
            }
          ],
          "org_metadata": {
            "league": "VĐQG Armenia",
            "team_a": "Ararat-Armenia",
            "team_b": "Gandzasar",
            "logo_a": "https://encrypted-tbn0.gstatic.com/images?q=tbn:ANd9GcS0kqWey0UfrC0EKfcwWbE__I45BpbqSL8o8Q&s",
            "logo_b": "https://media.api-sports.io/football/teams/688.png",
            "time": "22:00 27/05",
            "blv": "BLV TÁO MÈO",
            "is_live": false,
            "sport_slug": "bong-da"
          },
          "image": {
            "padding": 1,
            "background_color": "#ffffff",
            "display": "contain",
            "url": "https://raw.githubusercontent.com/jasminliu98/hoiquan-stream/refs/heads/main/thumbs/Ararat-Armenia_Gandzasar_22-00 27-05_3ee9cf51_20260527.png?v=3ee9cf51",
            "width": 1600,
            "height": 1200
          }
        },
        {
          "id": "hqlive-d8e137c2c8",
          "name": "Barcelona W vs Real Sociedad W | 00:00 28/05",
          "type": "single",
          "display": "thumbnail-only",
          "enable_detail": false,
          "labels": [
            {
              "text": "🕐 Sắp",
              "position": "top-left",
              "color": "#00000080",
              "text_color": "#aaaaaa"
            }
          ],
          "sources": [
            {
              "id": "src-d8e137c2c8",
              "name": "HoiQuanTV",
              "contents": [
                {
                  "id": "ct-d8e137c2c8",
                  "name": "Barcelona W vs Real Sociedad W",
                  "streams": [
                    {
                      "id": "st-d8e137c2c8",
                      "name": "HQ",
                      "stream_links": []
                    }
                  ]
                }
              ]
            }
          ],
          "org_metadata": {
            "league": "Primera División Femenina",
            "team_a": "Barcelona W",
            "team_b": "Real Sociedad W",
            "logo_a": "https://media.api-sports.io/football/teams/1918.png",
            "logo_b": "https://media.api-sports.io/football/teams/1912.png",
            "time": "00:00 28/05",
            "blv": "BLV TÁO GIÀ",
            "is_live": false,
            "sport_slug": "bong-da"
          },
          "image": {
            "padding": 1,
            "background_color": "#ffffff",
            "display": "contain",
            "url": "https://raw.githubusercontent.com/jasminliu98/hoiquan-stream/refs/heads/main/thumbs/Barcelona W_Real Sociedad W_00-00 28-05_eb859c7f_20260527.png?v=eb859c7f",
            "width": 1600,
            "height": 1200
          }
        },
        {
          "id": "hqlive-d621646992",
          "name": "Crystal Palace vs Rayo Vallecano | 02:00 28/05",
          "type": "single",
          "display": "thumbnail-only",
          "enable_detail": false,
          "labels": [
            {
              "text": "🕐 Sắp",
              "position": "top-left",
              "color": "#00000080",
              "text_color": "#aaaaaa"
            }
          ],
          "sources": [
            {
              "id": "src-d621646992",
              "name": "HoiQuanTV",
              "contents": [
                {
                  "id": "ct-d621646992",
                  "name": "Crystal Palace vs Rayo Vallecano",
                  "streams": [
                    {
                      "id": "st-d621646992",
                      "name": "HQ",
                      "stream_links": []
                    }
                  ]
                }
              ]
            }
          ],
          "org_metadata": {
            "league": "UEFA Europa Conference League",
            "team_a": "Crystal Palace",
            "team_b": "Rayo Vallecano",
            "logo_a": "https://upload.wikimedia.org/wikipedia/vi/a/a2/Crystal_Palace_FC_logo_%282022%29.svg.png",
            "logo_b": "https://upload.wikimedia.org/wikipedia/vi/0/03/Yyjbb92.png",
            "time": "02:00 28/05",
            "blv": "BLV TÁO MÈO, BLV THẦN THÔNG",
            "is_live": false,
            "sport_slug": "bong-da"
          },
          "image": {
            "padding": 1,
            "background_color": "#ffffff",
            "display": "contain",
            "url": "https://raw.githubusercontent.com/jasminliu98/hoiquan-stream/refs/heads/main/thumbs/Crystal Palace_Rayo Vallecano_02-00 28-05_af5ee8b9_20260527.png?v=af5ee8b9",
            "width": 1600,
            "height": 1200
          }
        },
        {
          "id": "hqlive-d86238f4c4",
          "name": "Fluminense vs Deportivo La Guaira | 07:30 28/05",
          "type": "single",
          "display": "thumbnail-only",
          "enable_detail": false,
          "labels": [
            {
              "text": "🕐 Sắp",
              "position": "top-left",
              "color": "#00000080",
              "text_color": "#aaaaaa"
            }
          ],
          "sources": [
            {
              "id": "src-d86238f4c4",
              "name": "HoiQuanTV",
              "contents": [
                {
                  "id": "ct-d86238f4c4",
                  "name": "Fluminense vs Deportivo La Guaira",
                  "streams": [
                    {
                      "id": "st-d86238f4c4",
                      "name": "HQ",
                      "stream_links": []
                    }
                  ]
                }
              ]
            }
          ],
          "org_metadata": {
            "league": "CONMEBOL Libertadores",
            "team_a": "Fluminense",
            "team_b": "Deportivo La Guaira",
            "logo_a": "https://ssl.gstatic.com/onebox/media/sports/logos/fCMxMMDF2AZPU7LzYKSlig_96x96.png",
            "logo_b": "https://media.api-sports.io/football/teams/2813.png",
            "time": "07:30 28/05",
            "blv": "BLV TÁO GIÀ",
            "is_live": false,
            "sport_slug": "bong-da"
          },
          "image": {
            "padding": 1,
            "background_color": "#ffffff",
            "display": "contain",
            "url": "https://raw.githubusercontent.com/jasminliu98/hoiquan-stream/refs/heads/main/thumbs/Fluminense_Deportivo La Guaira_07-30 28-05_72f84c67_20260527.png?v=72f84c67",
            "width": 1600,
            "height": 1200
          }
        },
        {
          "id": "hqlive-7ab556ad7d",
          "name": "River Plate vs Blooming | 07:30 28/05",
          "type": "single",
          "display": "thumbnail-only",
          "enable_detail": false,
          "labels": [
            {
              "text": "🕐 Sắp",
              "position": "top-left",
              "color": "#00000080",
              "text_color": "#aaaaaa"
            }
          ],
          "sources": [
            {
              "id": "src-7ab556ad7d",
              "name": "HoiQuanTV",
              "contents": [
                {
                  "id": "ct-7ab556ad7d",
                  "name": "River Plate vs Blooming",
                  "streams": [
                    {
                      "id": "st-7ab556ad7d",
                      "name": "HQ",
                      "stream_links": []
                    }
                  ]
                }
              ]
            }
          ],
          "org_metadata": {
            "league": "CONMEBOL Sudamericana",
            "team_a": "River Plate",
            "team_b": "Blooming",
            "logo_a": "https://upload.wikimedia.org/wikipedia/vi/4/41/River_Plate_logo.png",
            "logo_b": "https://media.api-sports.io/football/teams/3701.png",
            "time": "07:30 28/05",
            "blv": "BLV PHAN ANH",
            "is_live": false,
            "sport_slug": "bong-da"
          },
          "image": {
            "padding": 1,
            "background_color": "#ffffff",
            "display": "contain",
            "url": "https://raw.githubusercontent.com/jasminliu98/hoiquan-stream/refs/heads/main/thumbs/River Plate_Blooming_07-30 28-05_46d85a14_20260527.png?v=46d85a14",
            "width": 1600,
            "height": 1200
          }
        },
        {
          "id": "hqlive-7d516852a6",
          "name": "Okzhetpes vs Aktobe | 17:00 28/05",
          "type": "single",
          "display": "thumbnail-only",
          "enable_detail": false,
          "labels": [
            {
              "text": "🕐 Sắp",
              "position": "top-left",
              "color": "#00000080",
              "text_color": "#aaaaaa"
            }
          ],
          "sources": [
            {
              "id": "src-7d516852a6",
              "name": "HoiQuanTV",
              "contents": [
                {
                  "id": "ct-7d516852a6",
                  "name": "Okzhetpes vs Aktobe",
                  "streams": [
                    {
                      "id": "st-7d516852a6",
                      "name": "HQ",
                      "stream_links": []
                    }
                  ]
                }
              ]
            }
          ],
          "org_metadata": {
            "league": "Ngoại hạng Kazakhstan",
            "team_a": "Okzhetpes",
            "team_b": "Aktobe",
            "logo_a": "https://media.api-sports.io/football/teams/4558.png",
            "logo_b": "https://media.api-sports.io/football/teams/4563.png",
            "time": "17:00 28/05",
            "blv": "BLV TÁO GIÀ",
            "is_live": false,
            "sport_slug": "bong-da"
          },
          "image": {
            "padding": 1,
            "background_color": "#ffffff",
            "display": "contain",
            "url": "https://raw.githubusercontent.com/jasminliu98/hoiquan-stream/refs/heads/main/thumbs/Okzhetpes_Aktobe_17-00 28-05_23e41a8f_20260527.png?v=23e41a8f",
            "width": 1600,
            "height": 1200
          }
        },
        {
          "id": "hqlive-ad9a930407",
          "name": "Belgium U17 vs Spain U17 | 18:30 28/05",
          "type": "single",
          "display": "thumbnail-only",
          "enable_detail": false,
          "labels": [
            {
              "text": "🕐 Sắp",
              "position": "top-left",
              "color": "#00000080",
              "text_color": "#aaaaaa"
            }
          ],
          "sources": [
            {
              "id": "src-ad9a930407",
              "name": "HoiQuanTV",
              "contents": [
                {
                  "id": "ct-ad9a930407",
                  "name": "Belgium U17 vs Spain U17",
                  "streams": [
                    {
                      "id": "st-ad9a930407",
                      "name": "HQ",
                      "stream_links": []
                    }
                  ]
                }
              ]
            }
          ],
          "org_metadata": {
            "league": "UEFA U17 Championship",
            "team_a": "Belgium U17",
            "team_b": "Spain U17",
            "logo_a": "https://media.api-sports.io/football/teams/1.png",
            "logo_b": "https://upload.wikimedia.org/wikipedia/commons/thumb/8/89/Bandera_de_Espa%C3%B1a.svg/1280px-Bandera_de_Espa%C3%B1a.svg.png",
            "time": "18:30 28/05",
            "blv": "BLV TÁO KINH TẾ",
            "is_live": false,
            "sport_slug": "bong-da"
          },
          "image": {
            "padding": 1,
            "background_color": "#ffffff",
            "display": "contain",
            "url": "https://raw.githubusercontent.com/jasminliu98/hoiquan-stream/refs/heads/main/thumbs/Belgium U17_Spain U17_18-30 28-05_5c58ad3b_20260527.png?v=5c58ad3b",
            "width": 1600,
            "height": 1200
          }
        }
      ]
    },
    {
      "id": "sport_billiards",
      "name": "🎱 Billiards (1 LIVE)",
      "display": "vertical",
      "grid_number": 2,
      "enable_detail": false,
      "channels": [
        {
          "id": "hqlive-3eef201e14",
          "name": "Tay cơ 1 vs Tay cơ 2 | 21:00 27/05",
          "type": "single",
          "display": "thumbnail-only",
          "enable_detail": false,
          "labels": [
            {
              "text": "● LIVE",
              "position": "top-left",
              "color": "#00000080",
              "text_color": "#ff4444"
            }
          ],
          "sources": [
            {
              "id": "src-3eef201e14",
              "name": "HoiQuanTV",
              "contents": [
                {
                  "id": "ct-3eef201e14",
                  "name": "Tay cơ 1 vs Tay cơ 2",
                  "streams": [
                    {
                      "id": "st-3eef201e14",
                      "name": "HQ",
                      "stream_links": [
                        {
                          "id": "lnk-975fc55dd1",
                          "name": "BLV LƯƠNG BỔNG",
                          "type": "hls",
                          "default": true,
                          "url": "https://hqlive.yarncdn.live/live/hqtv_blv_phanliem/playlist.m3u8",
                          "request_headers": [
                            {
                              "key": "Referer",
                              "value": "https://sv2.hoiquan3.live/"
                            },
                            {
                              "key": "User-Agent",
                              "value": "Mozilla/5.0"
                            }
                          ]
                        }
                      ]
                    }
                  ]
                }
              ]
            }
          ],
          "org_metadata": {
            "league": "UK OPEN",
            "team_a": "Tay cơ 1",
            "team_b": "Tay cơ 2",
            "logo_a": "https://img.freepik.com/vector-mien-phi/mau-thiet-ke-logo-billiard_23-2150883890.jpg",
            "logo_b": "https://img.freepik.com/vector-mien-phi/mau-thiet-ke-logo-billiard_23-2150883890.jpg",
            "time": "21:00 27/05",
            "blv": "BLV LƯƠNG BỔNG",
            "is_live": true,
            "sport_slug": "billiards"
          },
          "image": {
            "padding": 1,
            "background_color": "#ffffff",
            "display": "contain",
            "url": "https://raw.githubusercontent.com/jasminliu98/hoiquan-stream/refs/heads/main/thumbs/Tay cơ 1_Tay cơ 2_21-00 27-05_97f1b445_20260527.png?v=97f1b445",
            "width": 1600,
            "height": 1200
          }
        }
      ]
    },
    {
      "id": "sport_cau-long",
      "name": "🏸 Cầu Lông (1 LIVE)",
      "display": "vertical",
      "grid_number": 2,
      "enable_detail": false,
      "channels": [
        {
          "id": "hqlive-99c216d0a1",
          "name": "Tay Vợt Số 1 vs Tay Vợt Số 2 | 15:00 27/05",
          "type": "single",
          "display": "thumbnail-only",
          "enable_detail": false,
          "labels": [
            {
              "text": "● LIVE",
              "position": "top-left",
              "color": "#00000080",
              "text_color": "#ff4444"
            }
          ],
          "sources": [
            {
              "id": "src-99c216d0a1",
              "name": "HoiQuanTV",
              "contents": [
                {
                  "id": "ct-99c216d0a1",
                  "name": "Tay Vợt Số 1 vs Tay Vợt Số 2",
                  "streams": [
                    {
                      "id": "st-99c216d0a1",
                      "name": "HQ",
                      "stream_links": [
                        {
                          "id": "lnk-eae8482cb7",
                          "name": "BLV PHAN BÁCH",
                          "type": "hls",
                          "default": true,
                          "url": "https://hqlive.yarncdn.live/live/hqtv_blv_phanchuot/playlist.m3u8",
                          "request_headers": [
                            {
                              "key": "Referer",
                              "value": "https://sv2.hoiquan3.live/"
                            },
                            {
                              "key": "User-Agent",
                              "value": "Mozilla/5.0"
                            }
                          ]
                        }
                      ]
                    }
                  ]
                }
              ]
            }
          ],
          "org_metadata": {
            "league": "KFF Singapore Badminton Open 2026",
            "team_a": "Tay Vợt Số 1",
            "team_b": "Tay Vợt Số 2",
            "logo_a": "https://static.flashscore.com/res/image/data/O2nuZwRp-vaAM5VhK.png",
            "logo_b": "https://static.flashscore.com/res/image/data/O2nuZwRp-vaAM5VhK.png",
            "time": "15:00 27/05",
            "blv": "BLV PHAN BÁCH",
            "is_live": true,
            "sport_slug": "cau-long"
          },
          "image": {
            "padding": 1,
            "background_color": "#ffffff",
            "display": "contain",
            "url": "https://raw.githubusercontent.com/jasminliu98/hoiquan-stream/refs/heads/main/thumbs/Tay Vợt Số 1_Tay Vợt Số 2_15-00 27-05_cacf1340_20260527.png?v=cacf1340",
            "width": 1600,
            "height": 1200
          }
        }
      ]
    },
    {
      "id": "sport_tennis",
      "name": "🎾 Tennis (1 LIVE)",
      "display": "vertical",
      "grid_number": 2,
      "enable_detail": false,
      "channels": [
        {
          "id": "hqlive-a28c741e53",
          "name": "Valentin Royer vs Novak Djokovic | 21:00 27/05",
          "type": "single",
          "display": "thumbnail-only",
          "enable_detail": false,
          "labels": [
            {
              "text": "● LIVE",
              "position": "top-left",
              "color": "#00000080",
              "text_color": "#ff4444"
            }
          ],
          "sources": [
            {
              "id": "src-a28c741e53",
              "name": "HoiQuanTV",
              "contents": [
                {
                  "id": "ct-a28c741e53",
                  "name": "Valentin Royer vs Novak Djokovic",
                  "streams": [
                    {
                      "id": "st-a28c741e53",
                      "name": "HQ",
                      "stream_links": [
                        {
                          "id": "lnk-ee33939914",
                          "name": "BLV PHAN TỪ",
                          "type": "hls",
                          "default": true,
                          "url": "https://hqlive.yarncdn.live/live/hqtv_blv_phantu/playlist.m3u8",
                          "request_headers": [
                            {
                              "key": "Referer",
                              "value": "https://sv2.hoiquan3.live/"
                            },
                            {
                              "key": "User-Agent",
                              "value": "Mozilla/5.0"
                            }
                          ]
                        }
                      ]
                    }
                  ]
                }
              ]
            }
          ],
          "org_metadata": {
            "league": "Roland Garros",
            "team_a": "Valentin Royer",
            "team_b": "Novak Djokovic",
            "logo_a": "https://encrypted-tbn0.gstatic.com/images?q=tbn:ANd9GcQVceA9jrHXNRuDxl74r2XUF6La-AxRYeuGJA&s",
            "logo_b": "https://media.cnn.com/api/v1/images/stellar/prod/gettyimages-2163072777-copy.jpg?c=original",
            "time": "21:00 27/05",
            "blv": "BLV PHAN TỪ",
            "is_live": true,
            "sport_slug": "tennis"
          },
          "image": {
            "padding": 1,
            "background_color": "#ffffff",
            "display": "contain",
            "url": "https://raw.githubusercontent.com/jasminliu98/hoiquan-stream/refs/heads/main/thumbs/Valentin Royer_Novak Djokovic_21-00 27-05_8a9fa08b_20260527.png?v=8a9fa08b",
            "width": 1600,
            "height": 1200
          }
        },
        {
          "id": "hqlive-3817d0812d",
          "name": "Tomas Machac vs Alexandet Zverev | 01:30 28/05",
          "type": "single",
          "display": "thumbnail-only",
          "enable_detail": false,
          "labels": [
            {
              "text": "🕐 Sắp",
              "position": "top-left",
              "color": "#00000080",
              "text_color": "#aaaaaa"
            }
          ],
          "sources": [
            {
              "id": "src-3817d0812d",
              "name": "HoiQuanTV",
              "contents": [
                {
                  "id": "ct-3817d0812d",
                  "name": "Tomas Machac vs Alexandet Zverev",
                  "streams": [
                    {
                      "id": "st-3817d0812d",
                      "name": "HQ",
                      "stream_links": []
                    }
                  ]
                }
              ]
            }
          ],
          "org_metadata": {
            "league": "Roland Garros",
            "team_a": "Tomas Machac",
            "team_b": "Alexandet Zverev",
            "logo_a": "https://encrypted-tbn0.gstatic.com/images?q=tbn:ANd9GcRFXdwaH9QMh6ZenXsa--g2VXiVPn7BuJjjbQ&s",
            "logo_b": "https://upload.wikimedia.org/wikipedia/commons/2/2e/Zverev_MCM23_%2820%29.jpg",
            "time": "01:30 28/05",
            "blv": "BLV PHAN TỪ",
            "is_live": false,
            "sport_slug": "tennis"
          },
          "image": {
            "padding": 1,
            "background_color": "#ffffff",
            "display": "contain",
            "url": "https://raw.githubusercontent.com/jasminliu98/hoiquan-stream/refs/heads/main/thumbs/Tomas Machac_Alexandet Zverev_01-30 28-05_8d2eccdf_20260527.png?v=8d2eccdf",
            "width": 1600,
            "height": 1200
          }
        }
      ]
    }
  ]
}